clipcount/__init__.py
clipcount/__main__.py
clipcount/cli.py
clipcount/core.py
clipcount/usage.py
clipcount-1.0.2.dist-info/entry_points.txt
clipcount-1.0.2.dist-info/licenses/LICENSE
clipcount-1.0.2.dist-info/METADATA
clipcount-1.0.2.dist-info/WHEEL
clipcount-1.0.2.dist-info/RECORD
